memory_client.py
memphora_sdk.py
memphora-1.3.4.dist-info/licenses/LICENSE
tests/__init__.py
tests/test_comprehensive.py
memphora-1.3.4.dist-info/METADATA
memphora-1.3.4.dist-info/WHEEL
memphora-1.3.4.dist-info/top_level.txt
memphora-1.3.4.dist-info/RECORD
